pyrpde/__init__.py
pyrpde-0.1.3.dist-info/LICENSE
pyrpde-0.1.3.dist-info/METADATA
pyrpde-0.1.3.dist-info/WHEEL
pyrpde-0.1.3.dist-info/top_level.txt
pyrpde-0.1.3.dist-info/RECORD
