Metadata-Version: 2.1
Name: pyrpde
Version: 0.1.3
Summary: A Python implementation of the Recurrence Period Density Entropy (RPDE)
Home-page: https://github.com/bootphon/pyrpde
Author: Hadrien Titeux & Rachid Riad
Author-email: hadrien.titeux@ens.fr
License: MIT
Platform: UNKNOWN
Classifier: Development Status :: 3 - Alpha
Classifier: License :: OSI Approved :: MIT License
Classifier: Programming Language :: Python :: 3.6
Requires-Dist: numba (>=0.49.1)
Requires-Dist: numpy (>=1.18.4)
Requires-Dist: scipy (>=1.4.1)
